[
  {
    "full_name": "homeport/termshot",
    "stargazers_count": 508,
    "open_issues_count": 24,
    "forks_count": 19
  },
  {
    "full_name": "charmbracelet/freeze",
    "stargazers_count": 3685,
    "open_issues_count": 56,
    "forks_count": 64
  },
  {
    "full_name": "freeCodeCamp/how-to-contribute-to-open-source",
    "stargazers_count": 8886,
    "open_issues_count": 69,
    "forks_count": 1839
  },
  {
    "full_name": "tedtay/Altair-Visulisation-Project",
    "stargazers_count": 1,
    "open_issues_count": 0,
    "forks_count": 0
  },
  {
    "full_name": "klembot/twinejs",
    "stargazers_count": 2216,
    "open_issues_count": 243,
    "forks_count": 326
  },
  {
    "full_name": "expressjs/body-parser",
    "stargazers_count": 5479,
    "open_issues_count": 35,
    "forks_count": 743
  },
  {
    "full_name": "expressjs/morgan",
    "stargazers_count": 8016,
    "open_issues_count": 21,
    "forks_count": 533
  },
  {
    "full_name": "ghosh/uiGradients",
    "stargazers_count": 5928,
    "open_issues_count": 226,
    "forks_count": 1394
  },
  {
    "full_name": "mwaskom/seaborn",
    "stargazers_count": 12944,
    "open_issues_count": 170,
    "forks_count": 1970
  },
  {
    "full_name": "matplotlib/matplotlib",
    "stargazers_count": 20890,
    "open_issues_count": 1634,
    "forks_count": 7792
  },
  {
    "full_name": "lgarron/folderify",
    "stargazers_count": 1709,
    "open_issues_count": 12,
    "forks_count": 38
  },
  {
    "full_name": "jupyter/jupyter",
    "stargazers_count": 15057,
    "open_issues_count": 44,
    "forks_count": 4200
  },
  {
    "full_name": "dylanaraps/pure-bash-bible",
    "stargazers_count": 36840,
    "open_issues_count": 61,
    "forks_count": 3310
  },
  {
    "full_name": "spaceship-prompt/spaceship-prompt",
    "stargazers_count": 19846,
    "open_issues_count": 132,
    "forks_count": 967
  },
  {
    "full_name": "ryanoasis/nerd-fonts",
    "stargazers_count": 56822,
    "open_issues_count": 18,
    "forks_count": 3714
  },
  {
    "full_name": "google/zx",
    "stargazers_count": 43761,
    "open_issues_count": 9,
    "forks_count": 1126
  },
  {
    "full_name": "ohmyzsh/ohmyzsh",
    "stargazers_count": 176800,
    "open_issues_count": 483,
    "forks_count": 26023
  },
  {
    "full_name": "bpkg/bpkg",
    "stargazers_count": 1918,
    "open_issues_count": 38,
    "forks_count": 98
  },
  {
    "full_name": "warpdotdev/Warp",
    "stargazers_count": 22540,
    "open_issues_count": 2679,
    "forks_count": 403
  },
  {
    "full_name": "MidnightCommander/mc-old",
    "stargazers_count": 2708,
    "open_issues_count": 27,
    "forks_count": 528
  },
  {
    "full_name": "starship/starship",
    "stargazers_count": 47585,
    "open_issues_count": 832,
    "forks_count": 2054
  },
  {
    "full_name": "charmbracelet/glow",
    "stargazers_count": 17328,
    "open_issues_count": 96,
    "forks_count": 389
  },
  {
    "full_name": "openseadragon/openseadragon",
    "stargazers_count": 3117,
    "open_issues_count": 450,
    "forks_count": 619
  },
  {
    "full_name": "inaturalist/inaturalist",
    "stargazers_count": 706,
    "open_issues_count": 550,
    "forks_count": 199
  },
  {
    "full_name": "Candygoblen123/TerrariaArmMac",
    "stargazers_count": 115,
    "open_issues_count": 7,
    "forks_count": 1
  },
  {
    "full_name": "brentirwin/if-react",
    "stargazers_count": 9,
    "open_issues_count": 2,
    "forks_count": 0
  },
  {
    "full_name": "remixz/react-fiction",
    "stargazers_count": 21,
    "open_issues_count": 2,
    "forks_count": 3
  },
  {
    "full_name": "jamiebuilds/the-super-tiny-compiler",
    "stargazers_count": 28154,
    "open_issues_count": 17,
    "forks_count": 2871
  },
  {
    "full_name": "historicalsource/hitchhikersguide",
    "stargazers_count": 973,
    "open_issues_count": 0,
    "forks_count": 125
  },
  {
    "full_name": "google/fonts",
    "stargazers_count": 18623,
    "open_issues_count": 1324,
    "forks_count": 2697
  }
]