[
  {
    "full_name": "dylanaraps/pure-bash-bible",
    "stargazers_count": 35674,
    "open_issues_count": 62,
    "forks_count": 3206
  },
  {
    "full_name": "spaceship-prompt/spaceship-prompt",
    "stargazers_count": 18991,
    "open_issues_count": 128,
    "forks_count": 962
  },
  {
    "full_name": "ryanoasis/nerd-fonts",
    "stargazers_count": 50372,
    "open_issues_count": 46,
    "forks_count": 3525
  },
  {
    "full_name": "google/zx",
    "stargazers_count": 40539,
    "open_issues_count": 78,
    "forks_count": 993
  },
  {
    "full_name": "ohmyzsh/ohmyzsh",
    "stargazers_count": 167562,
    "open_issues_count": 478,
    "forks_count": 25521
  },
  {
    "full_name": "bpkg/bpkg",
    "stargazers_count": 1864,
    "open_issues_count": 34,
    "forks_count": 96
  },
  {
    "full_name": "warpdotdev/Warp",
    "stargazers_count": 18172,
    "open_issues_count": 1838,
    "forks_count": 279
  },
  {
    "full_name": "MidnightCommander/mc",
    "stargazers_count": 2322,
    "open_issues_count": 29,
    "forks_count": 502
  },
  {
    "full_name": "starship/starship",
    "stargazers_count": 39798,
    "open_issues_count": 673,
    "forks_count": 1709
  },
  {
    "full_name": "charmbracelet/glow",
    "stargazers_count": 14493,
    "open_issues_count": 141,
    "forks_count": 314
  },
  {
    "full_name": "openseadragon/openseadragon",
    "stargazers_count": 2887,
    "open_issues_count": 458,
    "forks_count": 583
  },
  {
    "full_name": "inaturalist/inaturalist",
    "stargazers_count": 614,
    "open_issues_count": 523,
    "forks_count": 176
  },
  {
    "full_name": "Candygoblen123/TerrariaArmMac",
    "stargazers_count": 74,
    "open_issues_count": 7,
    "forks_count": 1
  },
  {
    "full_name": "brentirwin/if-react",
    "stargazers_count": 8,
    "open_issues_count": 2,
    "forks_count": 0
  },
  {
    "full_name": "remixz/react-fiction",
    "stargazers_count": 21,
    "open_issues_count": 2,
    "forks_count": 2
  },
  {
    "full_name": "jamiebuilds/the-super-tiny-compiler",
    "stargazers_count": 26368,
    "open_issues_count": 17,
    "forks_count": 2777
  },
  {
    "full_name": "historicalsource/hitchhikersguide",
    "stargazers_count": 949,
    "open_issues_count": 0,
    "forks_count": 124
  },
  {
    "full_name": "google/fonts",
    "stargazers_count": 17372,
    "open_issues_count": 1165,
    "forks_count": 2562
  },
  {
    "full_name": "storybookjs/storybook",
    "stargazers_count": 82363,
    "open_issues_count": 1807,
    "forks_count": 8934
  },
  {
    "full_name": "strapi/strapi",
    "stargazers_count": 59342,
    "open_issues_count": 652,
    "forks_count": 7413
  },
  {
    "full_name": "facebook/docusaurus",
    "stargazers_count": 52002,
    "open_issues_count": 321,
    "forks_count": 7758
  },
  {
    "full_name": "electron/electron",
    "stargazers_count": 111404,
    "open_issues_count": 930,
    "forks_count": 14798
  },
  {
    "full_name": "konstantinmuenster/notion-clone",
    "stargazers_count": 2850,
    "open_issues_count": 9,
    "forks_count": 318
  },
  {
    "full_name": "ShoroukAziz/notion_widgets",
    "stargazers_count": 458,
    "open_issues_count": 102,
    "forks_count": 2296
  },
  {
    "full_name": "transitive-bullshit/nextjs-notion-starter-kit",
    "stargazers_count": 5670,
    "open_issues_count": 136,
    "forks_count": 4952
  },
  {
    "full_name": "makenotion/notion-sdk-js",
    "stargazers_count": 4482,
    "open_issues_count": 25,
    "forks_count": 516
  },
  {
    "full_name": "mermaid-js/mermaid",
    "stargazers_count": 65905,
    "open_issues_count": 910,
    "forks_count": 5635
  },
  {
    "full_name": "protontypes/open-sustainable-technology",
    "stargazers_count": 1830,
    "open_issues_count": 61,
    "forks_count": 215
  },
  {
    "full_name": "electricitymaps/electricitymaps-contrib",
    "stargazers_count": 3242,
    "open_issues_count": 275,
    "forks_count": 877
  },
  {
    "full_name": "batnoter/batnoter",
    "stargazers_count": 2289,
    "open_issues_count": 21,
    "forks_count": 131
  }
]